LIGGGHTSER/__init__.py
LIGGGHTSER/calculation.py
LIGGGHTSER/files.py
LIGGGHTSER/fractal.py
LIGGGHTSER/friction.py
LIGGGHTSER/read.py
LIGGGHTSER/stickslip.py
LIGGGHTSER/variable.py
LIGGGHTSER/write.py
LIGGGHTSER/xyy.py
LIGGGHTSER-0.0.3.dist-info/METADATA
LIGGGHTSER-0.0.3.dist-info/WHEEL
LIGGGHTSER-0.0.3.dist-info/top_level.txt
LIGGGHTSER-0.0.3.dist-info/RECORD
