Metadata-Version: 2.1
Name: LIGGGHTSER
Version: 0.0.3
Summary: LIGGGHTSER is a program that is able to automatically read data file printed or dumped by LIGGGHTS software.
Home-page: UNKNOWN
Author: D
Author-email: wangdi819825@gmail.com
License: MIT
Platform: UNKNOWN
Classifier: License :: OSI Approved :: MIT License
Classifier: Programming Language :: Python
Classifier: Programming Language :: Python :: 3
Classifier: Programming Language :: Python :: 3.6
Classifier: Programming Language :: Python :: Implementation :: CPython
Classifier: Programming Language :: Python :: Implementation :: PyPy
Requires-Python: >=3.6.0
